nagios_historian/VERSION
nagios_historian/__init__.py
nagios_historian/__main__.py
nagios_historian/historian_check.py
nagios_historian/oauth2_token.py
nagios_historian/plugin_check.py
nagios_historian-0.6.7.data/data/VERSION/VERSION
nagios_historian-0.6.7.dist-info/DESCRIPTION.rst
nagios_historian-0.6.7.dist-info/METADATA
nagios_historian-0.6.7.dist-info/RECORD
nagios_historian-0.6.7.dist-info/WHEEL
nagios_historian-0.6.7.dist-info/entry_points.txt
nagios_historian-0.6.7.dist-info/metadata.json
nagios_historian-0.6.7.dist-info/top_level.txt
