Metadata-Version: 2.0
Name: nagios-historian
Version: 0.6.7
Summary: nagios historian plugin
Home-page: https://github.com/matiasgrana/nagios_historian
Author: Matias Graña
Author-email: maicolmatiasg@gmail.com
License: MIT
Platform: UNKNOWN
Classifier: Development Status :: 5 - Production/Stable
Classifier: Intended Audience :: System Administrators
Classifier: License :: OSI Approved :: MIT License
Classifier: Programming Language :: Python :: 3
Classifier: Programming Language :: Python :: 3 :: Only
Classifier: Topic :: System :: Monitoring
Requires-Dist: requests (>=2.19.1)
Requires-Dist: rstcheck
